datahtml/__about__.py
datahtml/__init__.py
datahtml/_utils.py
datahtml/agents.py
datahtml/base.py
datahtml/crawler.py
datahtml/defaults.py
datahtml/errors.py
datahtml/facebook.py
datahtml/google.py
datahtml/google_trends.py
datahtml/instagram.py
datahtml/news.py
datahtml/parsers.py
datahtml/py.typed
datahtml/rss.py
datahtml/site.py
datahtml/sitemap.py
datahtml/types.py
datahtml/url_index.py
datahtml/web.py
datahtml/wikidata.py
datahtml/youtube.py
datahtml/apis/__init__.py
datahtml/apis/youtube.py
datahtml/contrib/__init__.py
datahtml/contrib/chrome/__init__.py
datahtml/contrib/chrome/v5.py
datahtml/contrib/chrome/v6.py
datahtml/newspaper/article.py
datahtml/newspaper/cleaners.py
datahtml/newspaper/configuration.py
datahtml/newspaper/extractors.py
datahtml/newspaper/outputformatters.py
datahtml/newspaper/parsers.py
datahtml/newspaper/settings.py
datahtml/newspaper/text.py
datahtml/newspaper/urls.py
datahtml/newspaper/utils.py
datahtml/newspaper/version.py
datahtml/newspaper/resources/text/stopwords-en.txt
datahtml-0.6.0.dist-info/METADATA
datahtml-0.6.0.dist-info/WHEEL
datahtml-0.6.0.dist-info/licenses/LICENSE
datahtml-0.6.0.dist-info/RECORD
