Metadata-Version: 2.1
Name: datahtml
Version: 0.6.0
Summary: A lib to work with html and web data
Project-URL: Documentation, https://github.com/algorinfo/datahtml#readme
Project-URL: Issues, https://github.com/algorinfo/datahtml/issues
Project-URL: Source, https://github.com/algorinfo/datahtml
Author-email: Xavier Petit <nuxion@gmail.com>
License-File: LICENSE
Classifier: Development Status :: 4 - Beta
Classifier: Programming Language :: Python
Classifier: Programming Language :: Python :: 3.8
Classifier: Programming Language :: Python :: 3.9
Classifier: Programming Language :: Python :: 3.10
Classifier: Programming Language :: Python :: Implementation :: CPython
Classifier: Programming Language :: Python :: Implementation :: PyPy
Requires-Python: >=3.8
Requires-Dist: attrs
Requires-Dist: beautifulsoup4
Requires-Dist: extruct~=0.17.0
Requires-Dist: feedparser
Requires-Dist: httpx
Requires-Dist: lxml
Requires-Dist: pydantic>=2
Requires-Dist: ujson~=5.10.0
Provides-Extra: news
Requires-Dist: newspaper3k~=0.2.8; extra == 'news'
